{
    "horse_premium": {
        "x": 1219,
        "y": 504,
        "w": 142,
        "h": 86
    },
    "attack_icon": {
        "x": 1076,
        "y": 651,
        "w": 61,
        "h": 60
    },
    "confirm_attack": {
        "x": 1077,
        "y": 775,
        "w": 89,
        "h": 79
    },
    "attack_button": {
        "x": 1560,
        "y": 1085,
        "w": 373,
        "h": 41
    },
    "template_button": {
        "x": 1510,
        "y": 945,
        "w": 43,
        "h": 40
    },
    "horse_gold_coins": {
        "x": 667,
        "y": 501,
        "w": 82,
        "h": 81
    },
    "confirm_attack2": {
        "x": 1119,
        "y": 887,
        "w": 93,
        "h": 84
    },
    "reduce_icon": {
        "x": 1207,
        "y": 564,
        "w": 65,
        "h": 48
    },
    "arrow_left": {
        "x": 661,
        "y": 632,
        "w": 46,
        "h": 82
    },
    "clock_1h": {
        "x": 1053,
        "y": 624,
        "w": 40,
        "h": 47
    },
    "clock_30": {
        "x": 776,
        "y": 622,
        "w": 61,
        "h": 53
    },
    "clock_1h_bonus": {
        "x": 1053,
        "y": 624,
        "w": 40,
        "h": 47
    },
    "clock_30m_bonus": {
        "x": 776,
        "y": 622,
        "w": 61,
        "h": 53
    }
}